LICENSE.txt
MANIFEST.in
README.md
setup.py
nei/__init__.py
nei/cells.py
nei/cmd.py
nei/execute.py
nei/parser.py
nei/server.py
nei/styles.py
nei.egg-info/PKG-INFO
nei.egg-info/SOURCES.txt
nei.egg-info/dependency_links.txt
nei.egg-info/entry_points.txt
nei.egg-info/requires.txt
nei.egg-info/top_level.txt
nei/client/ansi_to_html.js
nei/client/buffer.js
nei/client/cell.js
nei/client/comm.js
nei/client/components.js
nei/client/index.html
nei/client/marked.min.js
nei/client/moon.js
nei/client/nei.css
nei/client/test.js
nei/client/util.js